malcolm/__init__.py
malcolm/_version_git.py
malcolm/compat.py
malcolm/imalcolm.py
malcolm/profiler.py
malcolm/syslogger.py
malcolm/testutil.py
malcolm/yamlutil.py
malcolm/core/__init__.py
malcolm/core/alarm.py
malcolm/core/camel.py
malcolm/core/concurrency.py
malcolm/core/context.py
malcolm/core/controller.py
malcolm/core/define.py
malcolm/core/errors.py
malcolm/core/future.py
malcolm/core/hook.py
malcolm/core/info.py
malcolm/core/loggable.py
malcolm/core/models.py
malcolm/core/moduleutil.py
malcolm/core/notifier.py
malcolm/core/part.py
malcolm/core/process.py
malcolm/core/request.py
malcolm/core/response.py
malcolm/core/stateset.py
malcolm/core/table.py
malcolm/core/tags.py
malcolm/core/timestamp.py
malcolm/core/views.py
malcolm/modules/__init__.py
malcolm/modules/ADAndor/__init__.py
malcolm/modules/ADAndor/blocks/__init__.py
malcolm/modules/ADAndor/blocks/andor_driver_block.yaml
malcolm/modules/ADAndor/blocks/andor_runnable_block.yaml
malcolm/modules/ADAndor/parts/__init__.py
malcolm/modules/ADAndor/parts/andordriverpart.py
malcolm/modules/ADAndor3/__init__.py
malcolm/modules/ADAndor3/blocks/ADAndor3_driver_block.yaml
malcolm/modules/ADAndor3/blocks/ADAndor3_runnable_block.yaml
malcolm/modules/ADAndor3/blocks/__init__.py
malcolm/modules/ADCore/__init__.py
malcolm/modules/ADCore/infos.py
malcolm/modules/ADCore/util.py
malcolm/modules/ADCore/blocks/__init__.py
malcolm/modules/ADCore/blocks/ffmpeg_plugin_block.yaml
malcolm/modules/ADCore/blocks/hdf_writer_block.yaml
malcolm/modules/ADCore/blocks/position_labeller_block.yaml
malcolm/modules/ADCore/blocks/stats_plugin_block.yaml
malcolm/modules/ADCore/includes/__init__.py
malcolm/modules/ADCore/includes/adbase_parts.yaml
malcolm/modules/ADCore/includes/filewriting_collection.yaml
malcolm/modules/ADCore/includes/ndarraybase_parts.yaml
malcolm/modules/ADCore/includes/ndpluginbase_parts.yaml
malcolm/modules/ADCore/parts/__init__.py
malcolm/modules/ADCore/parts/detectordriverpart.py
malcolm-6.3.dist-info/LICENSE
malcolm-6.3.dist-info/METADATA
malcolm-6.3.dist-info/WHEEL
malcolm-6.3.dist-info/entry_points.txt
malcolm-6.3.dist-info/top_level.txt
malcolm-6.3.dist-info/RECORD
