Metadata-Version: 2.1
Name: malcolm
Version: 6.3
Summary: Scanning in the middlelayer
Home-page: https://github.com/dls-controls/pymalcolm
Author: Tom Cobb
Author-email: tom.cobb@diamond.ac.uk
License: Apache License 2.0
Classifier: Development Status :: 5 - Production/Stable
Classifier: Intended Audience :: Developers
Classifier: Natural Language :: English
Classifier: Operating System :: POSIX :: Linux
Classifier: Programming Language :: Python :: 3.6
Classifier: Programming Language :: Python :: 3.7
Classifier: Programming Language :: Python :: 3.8
License-File: LICENSE
Requires-Dist: annotypes
Requires-Dist: cothread
Requires-Dist: h5py (==2.9.0)
Requires-Dist: ipython
Requires-Dist: matplotlib
Requires-Dist: numpy
Requires-Dist: p4p (==3.5.5)
Requires-Dist: packaging
Requires-Dist: plop
Requires-Dist: pygelf
Requires-Dist: ruamel.yaml
Requires-Dist: scanpointgenerator
Requires-Dist: scipy
Requires-Dist: tornado
Requires-Dist: vdsgen
Provides-Extra: dev
Requires-Dist: atomicwrites ; extra == 'dev'
Requires-Dist: black ; extra == 'dev'
Requires-Dist: coverage ; extra == 'dev'
Requires-Dist: doc8 ; extra == 'dev'
Requires-Dist: flake8 ; extra == 'dev'
Requires-Dist: isort ; extra == 'dev'
Requires-Dist: mock ; extra == 'dev'
Requires-Dist: mypy ; extra == 'dev'
Requires-Dist: nose ; extra == 'dev'
Requires-Dist: pylint ; extra == 'dev'
Requires-Dist: pytest ; extra == 'dev'
Requires-Dist: pytest-cov ; extra == 'dev'
Requires-Dist: pytest-black ; extra == 'dev'
Requires-Dist: pytest-flake8 ; extra == 'dev'
Requires-Dist: pytest-mypy ; extra == 'dev'
Requires-Dist: pytest-timeout ; extra == 'dev'
Requires-Dist: sphinx (==4.3.2) ; extra == 'dev'
Requires-Dist: sphinx-rtd-theme-github-versions ; extra == 'dev'
Requires-Dist: typing ; extra == 'dev'
Requires-Dist: types-mock ; extra == 'dev'
